textual_diastatic/__about__.py
textual_diastatic/__init__.py
textual_diastatic/diastatic.py
textual_diastatic/dp_v1.css
textual_diastatic/entry_points.py
textual_diastatic-0.0.2.dist-info/METADATA
textual_diastatic-0.0.2.dist-info/WHEEL
textual_diastatic-0.0.2.dist-info/entry_points.txt
textual_diastatic-0.0.2.dist-info/licenses/LICENSE.txt
textual_diastatic-0.0.2.dist-info/RECORD
