Metadata-Version: 2.4
Name: textual-diastatic
Version: 0.0.2
Project-URL: Documentation, https://github.com/AllPilsnersRLagers/textual-diastatic#readme
Project-URL: Issues, https://github.com/AllPilsnersRLagers/textual-diastatic/issues
Project-URL: Source, https://github.com/AllPilsnersRLagers/textual-diastatic
Author-email: AllPilsnersRLagers <166260567+AllPilsnersRLagers@users.noreply.github.com>
License-Expression: MIT
License-File: LICENSE.txt
Classifier: Development Status :: 4 - Beta
Classifier: Programming Language :: Python
Classifier: Programming Language :: Python :: 3.8
Classifier: Programming Language :: Python :: 3.9
Classifier: Programming Language :: Python :: 3.10
Classifier: Programming Language :: Python :: 3.11
Classifier: Programming Language :: Python :: 3.12
Classifier: Programming Language :: Python :: Implementation :: CPython
Classifier: Programming Language :: Python :: Implementation :: PyPy
Requires-Python: >=3.8
Requires-Dist: textual==3.0.0
